cats_presentation_rendering/__init__.py
cats_presentation_rendering-0.1.0.dist-info/licenses/LICENSE
cats_presentation_rendering-0.1.0.dist-info/METADATA
cats_presentation_rendering-0.1.0.dist-info/WHEEL
cats_presentation_rendering-0.1.0.dist-info/top_level.txt
cats_presentation_rendering-0.1.0.dist-info/RECORD
