Metadata-Version: 2.4
Name: cats_presentation-rendering
Version: 0.1.0
Summary: Display an embedded cat presentation
Home-page: https://github.com/your-username/cats_presentation-rendering
Author: Louati Mahdi
Author-email: louatimahdi390@gmail.com
Keywords: cats presentation document embed
Classifier: Programming Language :: Python :: 3
Classifier: License :: OSI Approved :: MIT License
Classifier: Operating System :: OS Independent
Classifier: Topic :: Multimedia :: Graphics
Requires-Python: >=3.6
License-File: LICENSE
Requires-Dist: ipython>=7.0.0
Dynamic: author
Dynamic: author-email
Dynamic: classifier
Dynamic: description
Dynamic: description-content-type
Dynamic: home-page
Dynamic: keywords
Dynamic: license-file
Dynamic: requires-dist
Dynamic: requires-python
Dynamic: summary
